{
  "decks": [
    {
      "id": "deck-rust-alapok",
      "name": "Rust alapok",
      "description": "Demo pakli Iteracio 5 bemutatohoz.",
      "cards": [
        {
          "id": "card-001",
          "front": "Mi az ownership a Rustban?",
          "back": "A memoriatulajdonlas egyedi, es megszabja ki felelos az eroforrasert.",
          "tags": [
            "memory",
            "ownership"
          ],
          "created_at": "2026-04-22T09:00:00Z",
          "updated_at": "2026-04-22T09:00:00Z"
        },
        {
          "id": "card-002",
          "front": "Mire jo a borrowing?",
          "back": "Hozzaferest ad at tulajdonjog-atadas nelkul.",
          "tags": [
            "borrow",
            "references"
          ],
          "created_at": "2026-04-22T09:01:00Z",
          "updated_at": "2026-04-22T09:01:00Z"
        },
        {
          "id": "card-003",
          "front": "Mit jelent a mutable referencia?",
          "back": "Valtoztathato hivatkozas; egyszerre csak egy lehet aktiv.",
          "tags": [
            "mutability"
          ],
          "created_at": "2026-04-22T09:02:00Z",
          "updated_at": "2026-04-22T09:02:00Z"
        },
        {
          "id": "card-004",
          "front": "Mi az Option szerepe?",
          "back": "A hianyzo erteket explicit modon kezeli.",
          "tags": [
            "enum",
            "null-safety"
          ],
          "created_at": "2026-04-22T09:03:00Z",
          "updated_at": "2026-04-22T09:03:00Z"
        },
        {
          "id": "card-005",
          "front": "Mi az Result szerepe?",
          "back": "Sikeres es hibas vegkimenetet tipusosan ad vissza.",
          "tags": [
            "error-handling"
          ],
          "created_at": "2026-04-22T09:04:00Z",
          "updated_at": "2026-04-22T09:04:00Z"
        },
        {
          "id": "card-006",
          "front": "Mikor hasznalunk TryFrom konverziot?",
          "back": "Bemeneti adat validalt domain tipussa alakitashoz.",
          "tags": [
            "conversion",
            "validation"
          ],
          "created_at": "2026-04-22T09:05:00Z",
          "updated_at": "2026-04-22T09:05:00Z"
        },
        {
          "id": "card-007",
          "front": "Mit old meg az Arc?",
          "back": "Megosztott, szalbiztos tulajdonlast ad referenciaszamlalassal.",
          "tags": [
            "shared-state"
          ],
          "created_at": "2026-04-22T09:06:00Z",
          "updated_at": "2026-04-22T09:06:00Z"
        },
        {
          "id": "card-008",
          "front": "Mire jo a macro_rules!?",
          "back": "Az ismetlodo boilerplate mintak kivaltasara.",
          "tags": [
            "macros"
          ],
          "created_at": "2026-04-22T09:07:00Z",
          "updated_at": "2026-04-22T09:07:00Z"
        },
        {
          "id": "card-009",
          "front": "Mit csinal a serde derive?",
          "back": "Automatikus Serialize es Deserialize implementaciot general.",
          "tags": [
            "serde",
            "json"
          ],
          "created_at": "2026-04-22T09:08:00Z",
          "updated_at": "2026-04-22T09:08:00Z"
        },
        {
          "id": "card-010",
          "front": "Miert fontos az atomikus mentes?",
          "back": "Nem marad felkesz vagy korrupt allapotfajl hiba eseten sem.",
          "tags": [
            "persistence"
          ],
          "created_at": "2026-04-22T09:09:00Z",
          "updated_at": "2026-04-22T09:09:00Z"
        },
        {
          "id": "card-011",
          "front": "Mire jo a shuffle?",
          "back": "Valtozatos sorrendet ad a tanulasi sessionben.",
          "tags": [
            "study-mode"
          ],
          "created_at": "2026-04-22T09:10:00Z",
          "updated_at": "2026-04-22T09:10:00Z"
        },
        {
          "id": "card-012",
          "front": "Mit mutat a progress bar?",
          "back": "Az ertekelt es osszes kartya aranyat.",
          "tags": [
            "ux"
          ],
          "created_at": "2026-04-22T09:11:00Z",
          "updated_at": "2026-04-22T09:11:00Z"
        },
        {
          "id": "card-013",
          "front": "Mi a JSON perzisztencia celja?",
          "back": "Az allapot ujrainditas utan is megmaradjon.",
          "tags": [
            "storage"
          ],
          "created_at": "2026-04-22T09:12:00Z",
          "updated_at": "2026-04-22T09:12:00Z"
        },
        {
          "id": "card-014",
          "front": "Mire jo a dashboard?",
          "back": "Gyors attekintest ad a paklikrol es a sessionokrol.",
          "tags": [
            "dashboard"
          ],
          "created_at": "2026-04-22T09:13:00Z",
          "updated_at": "2026-04-22T09:13:00Z"
        },
        {
          "id": "card-015",
          "front": "Mit jelent a manualis mentes?",
          "back": "A felhasznalo egy gombbal azonnal mentheti az allapotot.",
          "tags": [
            "save"
          ],
          "created_at": "2026-04-22T09:14:00Z",
          "updated_at": "2026-04-22T09:14:00Z"
        },
        {
          "id": "card-016",
          "front": "Mi a vegso beadando celja?",
          "back": "Reprodukalhato, modern, bemutathato desktop projekt atadasa.",
          "tags": [
            "release"
          ],
          "created_at": "2026-04-22T09:15:00Z",
          "updated_at": "2026-04-22T09:15:00Z"
        }
      ]
    }
  ],
  "active_deck": "deck-rust-alapok",
  "session": {
    "deck_id": null,
    "card_order": [],
    "current_index": 0,
    "show_back": false,
    "last_grade": null,
    "grades_by_card": [],
    "shuffle": false,
    "started_at": null,
    "ended_at": null
  },
  "session_history": [
    {
      "deck_id": "deck-rust-alapok",
      "started_at": "2026-04-22T09:20:00Z",
      "ended_at": "2026-04-22T09:27:00Z",
      "duration_seconds": 420,
      "total_cards": 16,
      "graded_cards": 16,
      "nehez_count": 3,
      "kozepes_count": 7,
      "konnyu_count": 6,
      "shuffle": true
    }
  ],
  "settings": {
    "theme": "light",
    "language": "hu"
  }
}